langchain_middleware_notepad/__init__.py
langchain_middleware_notepad/middleware.py
langchain_middleware_notepad/state.py
langchain_middleware_notepad/tools.py
langchain_notepad_middleware-0.1.1.dist-info/licenses/LICENSE
langchain_notepad_middleware-0.1.1.dist-info/METADATA
langchain_notepad_middleware-0.1.1.dist-info/WHEEL
langchain_notepad_middleware-0.1.1.dist-info/top_level.txt
langchain_notepad_middleware-0.1.1.dist-info/RECORD
