Metadata-Version: 2.4
Name: langchain-notepad-middleware
Version: 0.1.1
Summary: A LangChain agent middleware that provides a plain-text scratchpad/notepad.
Author-email: Izzet Sezer <sezer@imsezer.com>
License: MIT
Project-URL: Homepage, https://github.com/izzet-sezer/NotePadMiddleware
Project-URL: Repository, https://github.com/izzet-sezer/NotePadMiddleware
Project-URL: Issues, https://github.com/izzet-sezer/NotePadMiddleware/issues
Keywords: langchain,middleware,notepad,scratchpad,agent
Classifier: Programming Language :: Python :: 3
Classifier: License :: OSI Approved :: MIT License
Classifier: Operating System :: OS Independent
Classifier: Development Status :: 4 - Beta
Classifier: Intended Audience :: Developers
Classifier: Topic :: Software Development :: Libraries :: Python Modules
Requires-Python: >=3.10
License-File: LICENSE
Requires-Dist: langchain>=0.1.0
Requires-Dist: langchain-core>=0.1.0
Provides-Extra: dev
Requires-Dist: pytest; extra == "dev"
Dynamic: license-file
